nonebot_prevent_withdrawal/__init__.py
nonebot_prevent_withdrawal-0.2.0.dist-info/METADATA
nonebot_prevent_withdrawal-0.2.0.dist-info/WHEEL
nonebot_prevent_withdrawal-0.2.0.dist-info/top_level.txt
nonebot_prevent_withdrawal-0.2.0.dist-info/RECORD
