Metadata-Version: 2.1
Name: nonebot-prevent-withdrawal
Version: 0.2.0
Summary: 偷看群友撤回的消息
Author-email: zhongwen-4 <2401128923@qq.com>
License: MIT
Requires-Python: >=3.10
Requires-Dist: nonebot2>=2.3.3
Requires-Dist: nonebot-adapter-onebot>=2.4.5
Requires-Dist: nonebot-plugin-localstore>=0.7.1
Requires-Dist: httpx>=0.27.2
Requires-Dist: nonebot-plugin-alconna>=0.53.1
